luculia/__init__.py
luculia/__main__.py
luculia/comms/__init__.py
luculia/comms/base.py
luculia/comms/list.py
luculia/items/__init__.py
luculia/items/book.py
luculia/items/note.py
luculia/tools/__init__.py
luculia/tools/conf.py
luculia/tools/errs.py
luculia/tools/file.py
luculia/tools/path.py
luculia-0.1.0.dist-info/METADATA
luculia-0.1.0.dist-info/WHEEL
luculia-0.1.0.dist-info/entry_points.txt
luculia-0.1.0.dist-info/license.md
luculia-0.1.0.dist-info/top_level.txt
luculia-0.1.0.dist-info/RECORD
