Metadata-Version: 2.1
Name: luculia
Version: 0.1.0
Summary: A personal note-taking engine.
Home-page: UNKNOWN
Author: Stephen Malone
Author-email: mail@luculia.org
License: UNKNOWN
Project-URL: Changelog, https://github.com/luculia/luculia/blob/master/changes.md
Project-URL: Issues, https://github.com/luculia/luculia/issues
Project-URL: License, https://github.com/luculia/luculia/blob/master/license.md
Project-URL: Releases, https://github.com/luculia/luculia/releases
Keywords: personal command-line note databse
Platform: UNKNOWN
Classifier: Development Status :: 3 - Alpha
Classifier: Environment :: Console
Classifier: Intended Audience :: End Users/Desktop
Classifier: License :: OSI Approved :: BSD License
Classifier: Natural Language :: English
Classifier: Programming Language :: Python :: 3.8
Classifier: Topic :: Database
Requires-Python: >=3.8.0
Requires-Dist: Click (>=7.0)
Requires-Dist: toml (>=0.10.0)
